django_merged_inlines-1.0.3.dist-info/METADATA
django_merged_inlines-1.0.3.dist-info/RECORD
django_merged_inlines-1.0.3.dist-info/WHEEL
django_merged_inlines-1.0.3.dist-info/top_level.txt
merged_inlines/__init__.py
merged_inlines/admin.py
merged_inlines/static/admin/js/merged_inlines.js
merged_inlines/templates/admin/change_form_merged_inlines.html
merged_inlines/templatetags/.DS_Store
merged_inlines/templatetags/__init__.py
merged_inlines/templatetags/__init__.pyc
merged_inlines/templatetags/merged_inline_extras.py
merged_inlines/templatetags/merged_inline_extras.pyc
merged_inlines/templatetags/__pycache__/__init__.cpython-34.pyc
merged_inlines/templatetags/__pycache__/__init__.cpython-35.pyc
merged_inlines/templatetags/__pycache__/__init__.cpython-36.pyc
merged_inlines/templatetags/__pycache__/__init__.cpython-37.pyc
merged_inlines/templatetags/__pycache__/merged_inline_extras.cpython-34.pyc
merged_inlines/templatetags/__pycache__/merged_inline_extras.cpython-35.pyc
merged_inlines/templatetags/__pycache__/merged_inline_extras.cpython-36.pyc
merged_inlines/templatetags/__pycache__/merged_inline_extras.cpython-37.pyc
